paddleocr_onnx/__init__.py
paddleocr_onnx/dict/en_dict.txt
paddleocr_onnx/imaug/__init__.py
paddleocr_onnx/imaug/operators.py
paddleocr_onnx/infer/__init__.py
paddleocr_onnx/infer/predict_det.py
paddleocr_onnx/infer/predict_rec.py
paddleocr_onnx/infer/predict_system.py
paddleocr_onnx/infer/utility.py
paddleocr_onnx/models/en_PP-OCRv3_det_infer.onnx
paddleocr_onnx/models/en_PP-OCRv4_rec_infer.onnx
paddleocr_onnx/paddle_onnx.py
paddleocr_onnx/postprocess/__init__.py
paddleocr_onnx/postprocess/det.py
paddleocr_onnx/postprocess/rec.py
paddleocr_onnx/ppstructure/utility.py
paddleocr_onnx-0.5.1.dist-info/METADATA
paddleocr_onnx-0.5.1.dist-info/WHEEL
paddleocr_onnx-0.5.1.dist-info/RECORD
