Metadata-Version: 2.1
Name: paddleocr-onnx
Version: 0.5.1
Summary: 
Author: The Walnut AI
Author-email: support@thewalnut.ai
Requires-Python: >3.9,<3.13
Classifier: Programming Language :: Python :: 3
Classifier: Programming Language :: Python :: 3.10
Classifier: Programming Language :: Python :: 3.11
Classifier: Programming Language :: Python :: 3.12
Requires-Dist: numpy (>=1.26.4,<2.0.0)
Requires-Dist: opencv-python-headless (>=4.9.0.80,<5.0.0.0)
Requires-Dist: pillow (>=10.3.0,<11.0.0)
Requires-Dist: pyclipper (>=1.3.0.post5,<2.0.0)
Requires-Dist: shapely (>=2.0.4,<3.0.0)
Requires-Dist: six (>=1.16.0,<2.0.0)
